{
  "$schema": "https://raw.githubusercontent.com/dotnet/docfx/main/schemas/docfx.schema.json",
  "metadata": [
    {
      "src": [
        {
          "files": [
            "src/**/*.csproj"
          ],
          "src": "../"
        }
      ],
      "dest": "api",
      "properties": {
        "TargetFramework": "net8.0"
      },
      "disableGitFeatures": false,
      "disableDefaultFilter": false
    }
  ],
  "build": {
    "content": [
      {
        "files": [
          "**/*.{md,yml}"
        ],
        "exclude": [
          "_site/**"
        ]
      }
    ],
    "resource": [
      {
        "files": [
          "images/**"
        ]
      }
    ],
    "output": "../docs",
    "template": [
      "default",
      "modern",
      "modern-dark"
    ],
    "globalMetadata": {
      "_appName": "Wolfgang.RepoTemplateTest6",
      "_appTitle": "Wolfgang.RepoTemplateTest6 Documentation",
      "_enableSearch": true,
      "_appFooter": "Made with DocFX",
      "_disableSidebar": false,
      "_disableTocFilter": false,
      "_enableDarkMode": true,
      "_baseUrl": "https://Chris-Wolfgang.github.io/repo-template-test-6/",
      "pdf": true
    }
  }
}

